kitconcept.recipe.solr-1.0.0a3-py2.7-nspkg.pth
kitconcept/recipe/solr/__init__.py
kitconcept/recipe/solr/tests/__init__.py
kitconcept/recipe/solr/tests/test_docs.py
kitconcept.recipe.solr-1.0.0a3.dist-info/METADATA
kitconcept.recipe.solr-1.0.0a3.dist-info/WHEEL
kitconcept.recipe.solr-1.0.0a3.dist-info/entry_points.txt
kitconcept.recipe.solr-1.0.0a3.dist-info/namespace_packages.txt
kitconcept.recipe.solr-1.0.0a3.dist-info/top_level.txt
kitconcept.recipe.solr-1.0.0a3.dist-info/RECORD
