Metadata-Version: 2.1
Name: kitconcept.recipe.solr
Version: 1.0.0a3
Summary: Buildout recipe for Solr.
Home-page: https://github.com/kitconcept/kitconcept.recipe.solr
Author: kitconcept GmbH
Author-email: info@kitconcept.com
License: gpl
Keywords: plone buildout solr
Platform: UNKNOWN
Classifier: Development Status :: 3 - Alpha
Classifier: Framework :: Buildout
Classifier: Intended Audience :: Developers
Classifier: Topic :: Software Development :: Build Tools
Classifier: Programming Language :: Python
Classifier: Programming Language :: Python :: 2.7
Classifier: License :: OSI Approved :: GNU General Public License v2 (GPLv2)
Requires-Dist: setuptools
Requires-Dist: zc.buildout
Requires-Dist: zc.recipe.egg
Requires-Dist: collective.recipe.template
Requires-Dist: hexagonit.recipe.download
Provides-Extra: tests
Requires-Dist: zope.testing ; extra == 'tests'
Requires-Dist: zc.buildout[test] ; extra == 'tests'
Requires-Dist: mocker ; extra == 'tests'
